Metadata-Version: 1.0
Name: mediagoblin-private
Version: 0.1.1
Summary: Restrict the access of anonymous users
Home-page: https://code.maroufle.fr/jerome/mediagoblin-private
Author: Jerome Lebleu
Author-email: jerome.lebleu@mailoo.org
License: AGPLv3
Platform: UNKNOWN
